LICENSE
README.md
setup.py
s1300088_learn/__init__.py
s1300088_learn.egg-info/PKG-INFO
s1300088_learn.egg-info/SOURCES.txt
s1300088_learn.egg-info/dependency_links.txt
s1300088_learn.egg-info/requires.txt
s1300088_learn.egg-info/top_level.txt
s1300088_learn/statistics/__init__.py
s1300088_learn/statistics/itemFrequencies.py
s1300088_learn/visualization/__init__.py
s1300088_learn/visualization/heatMap.py