Metadata-Version: 2.1
Name: s1300088-learn
Version: 2024.7.1
Summary: This software is being developed at the University of Aizu, Aizu-Wakamatsu, Fukushima, Japan
Home-page: https://github.com/kanam33/s1300088_learn
Author: s1300088
Author-email: s1300088@u-aizu.ac.jp
License: GPLv3
Classifier: Development Status :: 5 - Production/Stable
Classifier: Programming Language :: Python :: 3
Classifier: License :: OSI Approved :: GNU General Public License v3 (GPLv3)
Classifier: Operating System :: OS Independent
Requires-Python: >=3.5
Provides-Extra: gpu
Provides-Extra: spark
Provides-Extra: dev
Provides-Extra: all
License-File: LICENSE
